mario/__init__.py
mario/version.py
mario/core/AttrData.py
mario/core/CoreIO.py
mario/core/__init__.py
mario/core/mariometadata.py
mario/log_exc/__init__.py
mario/log_exc/exceptions.py
mario/log_exc/logger.py
mario/settings/__int__.py
mario/settings/original_settings.yaml
mario/settings/settings.py
mario/settings/settings.yaml
mario/test/IOT.xlsx
mario/test/IOT_dummy.xlsx
mario/test/SUT.xlsx
mario/test/__init__.py
mario/test/mario_test.py
mario/tools/__init__.py
mario/tools/aggregation.py
mario/tools/constants.py
mario/tools/database_builder.py
mario/tools/excelhandler.py
mario/tools/figaro_metadata.csv
mario/tools/handshake_parsers.py
mario/tools/iodownloader.py
mario/tools/iomath.py
mario/tools/ioshock.py
mario/tools/parsers_id.py
mario/tools/parsersclass.py
mario/tools/plots.py
mario/tools/plots_manager.py
mario/tools/sectoradd.py
mario/tools/tableparser.py
mario/tools/tabletransform.py
mario/tools/utilities.py
mariopy-0.3.5.dist-info/LICENSE
mariopy-0.3.5.dist-info/METADATA
mariopy-0.3.5.dist-info/WHEEL
mariopy-0.3.5.dist-info/top_level.txt
mariopy-0.3.5.dist-info/RECORD
