Metadata-Version: 2.1
Name: mariopy
Version: 0.3.5
Summary: A python package for automating input-output (IO) calculations, models,visualization and scenario analysis
Home-page: https://github.com/it-is-me-mario/MARIO
Author: Mohammad Amin Tahavori, Lorenzo Rinaldi, Nicolo Golinucci
Author-email: amin.tahavori@enextgen.it
License: GNU General Public License v3.0
License-File: LICENSE
Requires-Dist: pandas==2.2.3
Requires-Dist: numpy==2.1.1
Requires-Dist: xlsxwriter==3.2.0
Requires-Dist: plotly
Requires-Dist: tabulate
Requires-Dist: openpyxl==3.1.0
Requires-Dist: IPython>=8.27.0
Requires-Dist: pymrio
Requires-Dist: pyyaml
